odoo/addons/stock_reserve_sale_mrp/README.rst
odoo/addons/stock_reserve_sale_mrp/__init__.py
odoo/addons/stock_reserve_sale_mrp/__manifest__.py
odoo/addons/stock_reserve_sale_mrp/i18n/stock_reserve_sale_mrp.pot
odoo/addons/stock_reserve_sale_mrp/static/description/icon.png
odoo/addons/stock_reserve_sale_mrp/tests/__init__.py
odoo/addons/stock_reserve_sale_mrp/tests/test_stock_reserve_sale_mrp.py
odoo/addons/stock_reserve_sale_mrp/wizard/__init__.py
odoo/addons/stock_reserve_sale_mrp/wizard/sale_stock_reserve.py
odoo13_addon_stock_reserve_sale_mrp-13.0.1.1.1.dev2.dist-info/METADATA
odoo13_addon_stock_reserve_sale_mrp-13.0.1.1.1.dev2.dist-info/WHEEL
odoo13_addon_stock_reserve_sale_mrp-13.0.1.1.1.dev2.dist-info/top_level.txt
odoo13_addon_stock_reserve_sale_mrp-13.0.1.1.1.dev2.dist-info/RECORD
