Metadata-Version: 2.1
Name: odoo13-addon-stock-reserve-sale-mrp
Version: 13.0.1.1.1.dev2
Summary: Stock Reserve Sales MRP
Home-page: https://github.com/OCA/stock-logistics-warehouse
Author: ForgeFlow, Odoo Community Association (OCA)
Author-email: support@odoo-community.org
License: AGPL-3
Platform: UNKNOWN
Classifier: Programming Language :: Python
Classifier: Framework :: Odoo
Classifier: Framework :: Odoo :: 13.0
Classifier: License :: OSI Approved :: GNU Affero General Public License v3
Requires-Python: >=3.5
Requires-Dist: odoo13-addon-stock-reserve-sale
Requires-Dist: odoo <13.1dev,>=13.0a
